diffusers/__init__.py
diffusers/configuration_utils.py
diffusers/dependency_versions_check.py
diffusers/dependency_versions_table.py
diffusers/image_processor.py
diffusers/optimization.py
diffusers/py.typed
diffusers/training_utils.py
diffusers/commands/__init__.py
diffusers/commands/diffusers_cli.py
diffusers/commands/env.py
diffusers/commands/fp16_safetensors.py
diffusers/experimental/__init__.py
diffusers/experimental/rl/__init__.py
diffusers/experimental/rl/value_guided_sampling.py
diffusers/loaders/__init__.py
diffusers/loaders/autoencoder.py
diffusers/loaders/controlnet.py
diffusers/loaders/ip_adapter.py
diffusers/loaders/lora.py
diffusers/loaders/lora_conversion_utils.py
diffusers/loaders/peft.py
diffusers/loaders/single_file.py
diffusers/loaders/single_file_utils.py
diffusers/loaders/textual_inversion.py
diffusers/loaders/unet.py
diffusers/loaders/utils.py
diffusers/models/__init__.py
diffusers/models/activations.py
diffusers/models/adapter.py
diffusers/models/attention.py
diffusers/models/attention_flax.py
diffusers/models/attention_processor.py
diffusers/models/controlnet.py
diffusers/models/controlnet_flax.py
diffusers/models/downsampling.py
diffusers/models/dual_transformer_2d.py
diffusers/models/embeddings.py
diffusers/models/embeddings_flax.py
diffusers/models/lora.py
diffusers/models/modeling_flax_pytorch_utils.py
diffusers/models/modeling_flax_utils.py
diffusers/models/modeling_outputs.py
diffusers/models/modeling_pytorch_flax_utils.py
diffusers/models/modeling_utils.py
diffusers/models/normalization.py
diffusers/models/prior_transformer.py
diffusers/models/resnet.py
diffusers/models/resnet_flax.py
diffusers/models/t5_film_transformer.py
diffusers/models/transformer_2d.py
diffusers/models/transformer_temporal.py
diffusers/models/unet_1d.py
diffusers/models/unet_1d_blocks.py
diffusers/models/unet_2d.py
diffusers/models/unet_2d_blocks.py
diffusers/models/unet_2d_condition.py
diffusers/models/upsampling.py
diffusers/models/vae_flax.py
souJpg_diffusers-0.27.2.dist-info/LICENSE
souJpg_diffusers-0.27.2.dist-info/METADATA
souJpg_diffusers-0.27.2.dist-info/WHEEL
souJpg_diffusers-0.27.2.dist-info/entry_points.txt
souJpg_diffusers-0.27.2.dist-info/top_level.txt
souJpg_diffusers-0.27.2.dist-info/RECORD
